checkers.cpython-312-darwin.so
bitads_security/checkers.cpython-312-darwin.so
src/__init__.py
src/checkers.c
src/checkers.cpython-312-darwin.so
bitads_security-0.2.3.dist-info/METADATA
bitads_security-0.2.3.dist-info/WHEEL
bitads_security-0.2.3.dist-info/top_level.txt
bitads_security-0.2.3.dist-info/RECORD
