Metadata-Version: 2.1
Name: bitads_security
Version: 0.2.3
Summary: A Cython module for secure hash checking
Home-page: https://github.com/yourusername/sensitive_module
Author: Your Name
Author-email: your.email@example.com
Classifier: Programming Language :: Python :: 3
Classifier: Programming Language :: Cython
Classifier: License :: OSI Approved :: MIT License
Classifier: Operating System :: OS Independent
Requires-Python: >=3.11
